carbonkivy/__init__.py
carbonkivy/app.py
carbonkivy/config.py
carbonkivy/devtools.py
carbonkivy/factory_registers.py
carbonkivy/utils.py
carbonkivy/behaviors/__init__.py
carbonkivy/behaviors/adaptive_behavior.py
carbonkivy/behaviors/background_color_behavior.py
carbonkivy/behaviors/declarative_behavior.py
carbonkivy/behaviors/elevation_behavior.py
carbonkivy/behaviors/hierarchical_layer_behavior.py
carbonkivy/behaviors/hover_behavior.py
carbonkivy/behaviors/selectable_behavior.py
carbonkivy/behaviors/selection_behavior.py
carbonkivy/behaviors/state_focus_behavior.py
carbonkivy/behaviors/tooltip_behavior.py
carbonkivy/data/IBMPlex/IBM_Plex_Mono/OFL.txt
carbonkivy/data/IBMPlex/IBM_Plex_Mono/static/IBMPlexMono-Bold.ttf
carbonkivy/data/IBMPlex/IBM_Plex_Mono/static/IBMPlexMono-BoldItalic.ttf
carbonkivy/data/IBMPlex/IBM_Plex_Mono/static/IBMPlexMono-ExtraLight.ttf
carbonkivy/data/IBMPlex/IBM_Plex_Mono/static/IBMPlexMono-ExtraLightItalic.ttf
carbonkivy/data/IBMPlex/IBM_Plex_Mono/static/IBMPlexMono-Italic.ttf
carbonkivy/data/IBMPlex/IBM_Plex_Mono/static/IBMPlexMono-Light.ttf
carbonkivy/data/IBMPlex/IBM_Plex_Mono/static/IBMPlexMono-LightItalic.ttf
carbonkivy/data/IBMPlex/IBM_Plex_Mono/static/IBMPlexMono-Medium.ttf
carbonkivy/data/IBMPlex/IBM_Plex_Mono/static/IBMPlexMono-MediumItalic.ttf
carbonkivy/data/IBMPlex/IBM_Plex_Mono/static/IBMPlexMono-Regular.ttf
carbonkivy/data/IBMPlex/IBM_Plex_Mono/static/IBMPlexMono-SemiBold.ttf
carbonkivy/data/IBMPlex/IBM_Plex_Mono/static/IBMPlexMono-SemiBoldItalic.ttf
carbonkivy/data/IBMPlex/IBM_Plex_Mono/static/IBMPlexMono-Thin.ttf
carbonkivy/data/IBMPlex/IBM_Plex_Mono/static/IBMPlexMono-ThinItalic.ttf
carbonkivy/data/IBMPlex/IBM_Plex_Sans/OFL.txt
carbonkivy/data/IBMPlex/IBM_Plex_Sans/static/IBMPlexSans-Bold.ttf
carbonkivy/data/IBMPlex/IBM_Plex_Sans/static/IBMPlexSans-BoldItalic.ttf
carbonkivy/data/IBMPlex/IBM_Plex_Sans/static/IBMPlexSans-ExtraLight.ttf
carbonkivy/data/IBMPlex/IBM_Plex_Sans/static/IBMPlexSans-ExtraLightItalic.ttf
carbonkivy-0.0.4.dist-info/licenses/LICENSE
carbonkivy-0.0.4.dist-info/METADATA
carbonkivy-0.0.4.dist-info/WHEEL
carbonkivy-0.0.4.dist-info/top_level.txt
carbonkivy-0.0.4.dist-info/RECORD
