Metadata-Version: 2.4
Name: carbonkivy
Version: 0.0.4
Summary: CarbonKivy is a Python library that integrates IBM's Carbon Design System with the Kivy framework. It provides a modern, accessible, and user-friendly UI toolkit inspired by Carbon’s design principles, enabling developers to create consistent and visually appealing applications in Kivy.
Author-email: Kartavya Shukla <novfensec@protonmail.com>
Maintainer-email: Kartavya Shukla <novfensec@protonmail.com>
License-Expression: MIT
Project-URL: Homepage, https://github.com/Novfensec/CarbonKivy
Project-URL: Repository, https://github.com/Novfensec/CarbonKivy
Project-URL: Bug Tracker, https://github.com/Novfensec/CarbonKivy/issues
Project-URL: Changelog, https://github.com/Novfensec/CarbonKivy/blob/master/CHANGELOG.md
Keywords: kivy,python,open source,carbon,design,carbondesignsystem,IBM,novfensec,carbonkivy,kv,android,desktop,user-interface
Classifier: Development Status :: 5 - Production/Stable
Classifier: Intended Audience :: Developers
Classifier: Topic :: Software Development :: Libraries
Classifier: Topic :: Multimedia :: Graphics
Classifier: Programming Language :: Python :: 3
Requires-Python: >=3.10
License-File: LICENSE
Requires-Dist: kivy>=2.0.0
Dynamic: license-file
